remoteinfra/__init__.py
remoteinfra/dashboard.py
remoteinfra/remoteinfra.py
remoteinfra/UI/index.html
remoteinfra/UI/script.js
remoteinfra/UI/styles.css
remoteinfra/utils.py
remoteinfra-1.0.2.dist-info/entry_points.txt
remoteinfra-1.0.2.dist-info/licenses/LICENSE
remoteinfra-1.0.2.dist-info/METADATA
remoteinfra-1.0.2.dist-info/WHEEL
remoteinfra-1.0.2.dist-info/RECORD
